display_ht16k33/__init__.py
display_ht16k33/ht16k33.py
display_ht16k33/matrix.py
display_ht16k33/segments.py
circuitpython_display_ht16k33-1.0.2.dist-info/LICENSE
circuitpython_display_ht16k33-1.0.2.dist-info/METADATA
circuitpython_display_ht16k33-1.0.2.dist-info/WHEEL
circuitpython_display_ht16k33-1.0.2.dist-info/top_level.txt
circuitpython_display_ht16k33-1.0.2.dist-info/RECORD
