Metadata-Version: 2.2
Name: circuitpython-display_ht16k33
Version: 1.0.2
Summary: On Display Simulation for an HT16K33 driver. Works with 16x8 and 8x8 matrices.
Author-email: JDM <xxxy@mozmail.com>
License: MIT
Project-URL: Homepage, https://github.com/jposada202020/CircuitPython_DISPLAY_HT16K33
Keywords: sensor,blinka,circuitpython,micropython,display_ht16k33,ht16k33,displayio,matrix,8x8,16x8,display
Classifier: Intended Audience :: Developers
Classifier: Topic :: Software Development :: Libraries
Classifier: Topic :: Software Development :: Embedded Systems
Classifier: Topic :: System :: Hardware
Classifier: License :: OSI Approved :: MIT License
Classifier: Programming Language :: Python :: 3
License-File: LICENSE
Requires-Dist: Adafruit-Blinka
Provides-Extra: optional
